scp_servicenow/__init__.py
scp_servicenow/cli.py
scp_servicenow/cli_helpers.py
scp_servicenow/client.py
scp_servicenow/config.py
scp_servicenow/mapper.py
scp_servicenow/sync.py
scp_servicenow-0.1.3.dist-info/METADATA
scp_servicenow-0.1.3.dist-info/WHEEL
scp_servicenow-0.1.3.dist-info/entry_points.txt
scp_servicenow-0.1.3.dist-info/RECORD
