Metadata-Version: 2.4
Name: scp-servicenow
Version: 0.1.3
Summary: ServiceNow CMDB integration for SCP unified model
Project-URL: Homepage, https://systemcapabilityprotocol.com/
Project-URL: Documentation, https://systemcapabilityprotocol.com/integrations
Project-URL: Repository, https://github.com/krackenservices/scp-integrations.git
Project-URL: Issues, https://github.com/krackenservices/scp-integrations/issues
Author-email: Kracken Services <scp@krackenservices.com>
License: MIT
Keywords: cmdb,integration,itsm,scp,servicenow
Classifier: Development Status :: 4 - Beta
Classifier: Environment :: Console
Classifier: Intended Audience :: Developers
Classifier: Intended Audience :: System Administrators
Classifier: License :: OSI Approved :: MIT License
Classifier: Operating System :: OS Independent
Classifier: Programming Language :: Python :: 3
Classifier: Programming Language :: Python :: 3.12
Classifier: Programming Language :: Python :: 3.13
Classifier: Topic :: System :: Systems Administration
Classifier: Typing :: Typed
Requires-Python: >=3.12
Requires-Dist: httpx>=0.25
Requires-Dist: pydantic>=2.0
Requires-Dist: pyyaml>=6.0.3
Requires-Dist: rich>=13.0
Requires-Dist: scp-sdk>=0.2.0
Requires-Dist: typer>=0.9
